odoo/addons/pos_place/README.rst
odoo/addons/pos_place/__init__.py
odoo/addons/pos_place/__manifest__.py
odoo/addons/pos_place/demo/pos_config.xml
odoo/addons/pos_place/demo/pos_place.xml
odoo/addons/pos_place/demo/res_groups.xml
odoo/addons/pos_place/i18n/es.po
odoo/addons/pos_place/i18n/fr.po
odoo/addons/pos_place/i18n/pos_place.pot
odoo/addons/pos_place/models/__init__.py
odoo/addons/pos_place/models/account_invoice.py
odoo/addons/pos_place/models/pos_config.py
odoo/addons/pos_place/models/pos_order.py
odoo/addons/pos_place/models/pos_place.py
odoo/addons/pos_place/readme/CONFIGURE.rst
odoo/addons/pos_place/readme/CONTRIBUTORS.rst
odoo/addons/pos_place/readme/DESCRIPTION.rst
odoo/addons/pos_place/readme/USAGE.rst
odoo/addons/pos_place/report/__init__.py
odoo/addons/pos_place/report/report_pos_order.py
odoo/addons/pos_place/security/ir.model.access.csv
odoo/addons/pos_place/security/ir_module_category.xml
odoo/addons/pos_place/security/ir_rule.xml
odoo/addons/pos_place/security/res_groups.xml
odoo/addons/pos_place/static/description/icon.png
odoo/addons/pos_place/static/description/index.html
odoo/addons/pos_place/static/description/pos_front_end_ui.png
odoo/addons/pos_place/static/description/pos_order_tree.png
odoo/addons/pos_place/static/description/pos_place_tree.png
odoo/addons/pos_place/static/description/report_pos_order_graph.png
odoo/addons/pos_place/static/src/js/chrome.js
odoo/addons/pos_place/static/src/js/gui.js
odoo/addons/pos_place/static/src/js/models.js
odoo/addons/pos_place/static/src/js/widget.js
odoo/addons/pos_place/static/src/xml/pos_place.xml
odoo/addons/pos_place/views/templates.xml
odoo/addons/pos_place/views/view_account_invoice.xml
odoo/addons/pos_place/views/view_pos_config.xml
odoo/addons/pos_place/views/view_pos_order.xml
odoo/addons/pos_place/views/view_pos_place.xml
odoo12_addon_pos_place-12.0.1.0.4.dist-info/METADATA
odoo12_addon_pos_place-12.0.1.0.4.dist-info/WHEEL
odoo12_addon_pos_place-12.0.1.0.4.dist-info/top_level.txt
odoo12_addon_pos_place-12.0.1.0.4.dist-info/RECORD
